{
  "flyers_host": "https://cdn-gateflipp.flippback.com/bf/flipp",
  "item_shape": "D",
  "flyer_count": 113,
  "wanted_flyers": 11,
  "wrote": 161,
  "per_store": {
    "sobeys-glendale": 41,
    "freshco-scott": 18,
    "walmart-stcatharines": 46,
    "gianttiger-stcatharines": 22,
    "foodbasics-welland": 34
  },
  "flyer_diagnostics": [
    {
      "merchant": "Sobeys",
      "store_id": "sobeys-glendale",
      "flyer_id": 7941592,
      "raw_items": 400,
      "usable_items": 362,
      "matched": 41
    },
    {
      "merchant": "FreshCo",
      "store_id": "freshco-scott",
      "flyer_id": 7911230,
      "raw_items": 22,
      "usable_items": 22,
      "matched": 1
    },
    {
      "merchant": "Walmart",
      "store_id": "walmart-stcatharines",
      "flyer_id": 7880852,
      "raw_items": 227,
      "usable_items": 178,
      "matched": 0
    },
    {
      "merchant": "Walmart",
      "store_id": "walmart-stcatharines",
      "flyer_id": 7932692,
      "raw_items": 501,
      "usable_items": 458,
      "matched": 33
    },
    {
      "merchant": "Giant Tiger",
      "store_id": "gianttiger-stcatharines",
      "flyer_id": 7925015,
      "raw_items": 162,
      "usable_items": 148,
      "matched": 8
    },
    {
      "merchant": "Walmart",
      "store_id": "walmart-stcatharines",
      "flyer_id": 7912655,
      "raw_items": 201,
      "usable_items": 145,
      "matched": 5
    },
    {
      "merchant": "FreshCo",
      "store_id": "freshco-scott",
      "flyer_id": 7932482,
      "raw_items": 213,
      "usable_items": 209,
      "matched": 17
    },
    {
      "merchant": "Walmart",
      "store_id": "walmart-stcatharines",
      "flyer_id": 7917791,
      "raw_items": 55,
      "usable_items": 53,
      "matched": 7
    },
    {
      "merchant": "Walmart",
      "store_id": "walmart-stcatharines",
      "flyer_id": 7889198,
      "raw_items": 273,
      "usable_items": 225,
      "matched": 1
    },
    {
      "merchant": "Giant Tiger",
      "store_id": "gianttiger-stcatharines",
      "flyer_id": 7948911,
      "raw_items": 131,
      "usable_items": 115,
      "matched": 14
    },
    {
      "merchant": "Food Basics",
      "store_id": "foodbasics-welland",
      "flyer_id": 7932345,
      "raw_items": 391,
      "usable_items": 387,
      "matched": 34
    }
  ],
  "all_merchants": {
    "Metro": 5,
    "Home Hardware": 5,
    "Walmart": 5,
    "Leon's": 4,
    "Healthy Planet": 4,
    "Long & McQuade Musical Instruments": 3,
    "Pet Valu": 3,
    "I.D.A.": 3,
    "Ren's Pets": 3,
    "Pharmasave": 2,
    "Commisso's Fresh Foods": 2,
    "Sleep Country Canada": 2,
    "Costco": 2,
    "Paulmac's Pets": 2,
    "Shoppers Drug Mart": 2,
    "Princess Auto": 2,
    "Canadian Tire": 2,
    "PetSmart": 2,
    "FreshCo": 2,
    "Real Canadian Superstore": 2,
    "Giant Tiger": 2,
    "Tepperman's": 2,
    "Ray James Appliances": 2,
    "Cabela's & Bass Pro": 2,
    "The Brick": 2,
    "Best Buy": 1,
    "Dollarama": 1,
    "Party City": 1,
    "Nature's Source and Nature's Signature": 1,
    "Newegg": 1,
    "RONA & RONA +": 1,
    "Subway": 1,
    "Farm Boy": 1,
    "Piries Appliances": 1,
    "Bath Depot": 1,
    "GP Bikes": 1,
    "Surplus Furniture & Mattress Warehouse": 1,
    "Sobeys": 1,
    "Home Depot": 1,
    "Holt Renfrew": 1,
    "Cosmaroma": 1,
    "Oxford Mills": 1,
    "PartSource": 1,
    "Foodland": 1,
    "On the Run": 1,
    "EB Games Canada": 1,
    "Flipp Hottest Deals": 1,
    "Rexall": 1,
    "No Frills": 1,
    "IKEA": 1,
    "Product of the Year Canada": 1,
    "PharmaChoice": 1,
    "Michaels Canada": 1,
    "Canadian Grand Prix New Product Awards": 1,
    "M&M Food Market": 1,
    "Wholehealth Pharmacy": 1,
    "Zehrs": 1,
    "H&M": 1,
    "Your Independent Grocer": 1,
    "Big Red Markets": 1,
    "President's Choice": 1,
    "Kitchen Stuff Plus": 1,
    "Sephora": 1,
    "Staples": 1,
    "JYSK": 1,
    "The Shopping Channel": 1,
    "Hart Stores": 1,
    "Food Basics": 1,
    "Well.ca": 1,
    "Wholesale Club and Club Entrep\u00f4t": 1,
    "LCBO": 1
  }
}